README.rst
setup.py
pyrlamento.egg-info/PKG-INFO
pyrlamento.egg-info/SOURCES.txt
pyrlamento.egg-info/dependency_links.txt
pyrlamento.egg-info/requires.txt
pyrlamento.egg-info/top_level.txt
src/__init__.py
src/__main__.py
src/data.py
src/db.py
src/fetcher.py
src/pyrlamento.py
src/countries/__init__.py
src/countries/portugal/__init__.py
src/countries/portugal/data.py
src/countries/portugal/dre.py
src/countries/portugal/parlamento.py