Metadata-Version: 1.1
Name: pyrlamento
Version: 0.0.2
Summary: Generic interface to legal systems
Home-page: https://gitlab.com/claudiop/pyrlamento
Author: Cláudio Pereira
Author-email: development@claudiop.com
License: GPL V3
Keywords: law,interface,wrapper
Platform: UNKNOWN
Classifier: Development Status :: 3 - Alpha
Classifier: Topic :: Utilities
Classifier: License :: OSI Approved :: GNU General Public License v3 (GPLv3)
Classifier: Topic :: Internet :: WWW/HTTP
Classifier: Topic :: Internet :: WWW/HTTP :: Dynamic Content
Classifier: Topic :: Text Processing :: Markup :: HTML
